{"models":{"AchievementEntity":{"id":"AchievementEntity","properties":{"achievement_id":{"description":"ID of the Achievement Record","$ref":"id"},"name":{"type":"string","description":"Name of the achievement"},"children":{"type":"array","description":"Array of requirements","items":{"$ref":"AchievementEntity"}},"description":{"type":"string","description":"Detailed description of the achievement"}}}},"produces":["application/xml","application/json","application/octet-stream","text/plain"],"resourcePath":"/achievements","apiVersion":"v1","swaggerVersion":"1.2","apis":[{"operations":[{"parameters":[{"required":true,"name":"X-Partner-Token","paramType":"header","type":"string","description":"Your secret partner token"},{"required":true,"name":"X-User-Token","paramType":"header","type":"string","description":"The token you recieved when you authenticated the user"},{"required":false,"name":"id","paramType":"path","allowMultiple":false,"type":"string","description":""},{"format":"int32","required":true,"name":"award_type_id","paramType":"query","allowMultiple":false,"type":"integer","description":null}],"nickname":"GET--version-achievements--id","summary":"Returns detailed information about an achievement","notes":"","type":"AchievementEntity","method":"GET","responseMessages":[{"message":"401 Unauthorized partner","code":401},{"message":"401 Unauthorized user","code":401},{"message":"404 Achievement not found","code":404}]}],"path":"/v1/achievements/{id}"},{"operations":[{"parameters":[{"required":true,"name":"X-Partner-Token","paramType":"header","type":"string","description":"Your secret partner token"},{"required":true,"name":"X-User-Token","paramType":"header","type":"string","description":"The token you recieved when you authenticated the user"}],"nickname":"GET--version-achievements","summary":"Returns a list of available achievements for the member","notes":"","type":"AchievementEntity","method":"GET","responseMessages":[{"message":"Unauthorized Partner","code":401},{"message":"Unauthorized User","code":401}]}],"path":"/v1/achievements"}],"basePath":"https://trooptrack.com/api"}